setup.cfg
setup.py
otpsecure/__init__.py
otpsecure/base.py
otpsecure/callback.py
otpsecure/client.py
otpsecure/document.py
otpsecure/error.py
otpsecure/otp.py
otpsecure/status.py
otpsecure.egg-info/PKG-INFO
otpsecure.egg-info/SOURCES.txt
otpsecure.egg-info/dependency_links.txt
otpsecure.egg-info/requires.txt
otpsecure.egg-info/top_level.txt