Metadata-Version: 1.1
Name: otpsecure
Version: 1.0.6
Summary: OtpSecure's Python SDK
Home-page: https://github.com/ecertic/otpsecure_pyton-sdk
Author: OtpSecure
Author-email: sistemas@ecertic.com
License: BSD-2-Clause
Download-URL: https://github.com/ecertic/otpsecure_pyton-sdk/tarball/1.0.6
Keywords: otpsecure,sms
Platform: UNKNOWN
